lambda_powertuner/__init__.py
lambda_powertuner/py.typed
lambda_powertuner/_jsii/__init__.py
lambda_powertuner/_jsii/cdk-lambda-powertuner@0.2.0.jsii.tgz
cdk_lambda_powertuner-0.2.0.dist-info/METADATA
cdk_lambda_powertuner-0.2.0.dist-info/WHEEL
cdk_lambda_powertuner-0.2.0.dist-info/top_level.txt
cdk_lambda_powertuner-0.2.0.dist-info/RECORD
